raw_sugar/__init__.py
raw_sugar/managers.py
raw_sugar/query.py
raw_sugar/sources.py
tests/__init__.py
tests/models.py
tests/settings.py
tests/test_querying.py
django_raw_sugar-0.1.18.dist-info/LICENSE
django_raw_sugar-0.1.18.dist-info/METADATA
django_raw_sugar-0.1.18.dist-info/WHEEL
django_raw_sugar-0.1.18.dist-info/top_level.txt
django_raw_sugar-0.1.18.dist-info/RECORD
